hardware_control/__init__.py
hardware_control/_version.py
hardware_control/base/App.py
hardware_control/base/Dataset.py
hardware_control/base/HCMainWindow.py
hardware_control/base/Instrument.py
hardware_control/base/ZMQAdapter.py
hardware_control/base/ZMQRemoteAdapter.py
hardware_control/base/__init__.py
hardware_control/base/hooks.py
hardware_control/base/logging.py
hardware_control/base/zmq_helper.py
hardware_control/gui/__init__.py
hardware_control/gui/controls/DelayGenerator.py
hardware_control/gui/controls/DeviceTemplate.py
hardware_control/gui/controls/FlowController.py
hardware_control/gui/controls/FunctionGenerator.py
hardware_control/gui/controls/IOModule.py
hardware_control/gui/controls/KeysightPowerSupply.py
hardware_control/gui/controls/MicrowaveControl.py
hardware_control/gui/controls/MultiPowerSupply.py
hardware_control/gui/controls/Oscilloscope.py
hardware_control/gui/controls/RGA.py
hardware_control/gui/controls/TempMonitor.py
hardware_control/gui/controls/TempMonitor_Adam.py
hardware_control/gui/controls/__init__.py
hardware_control/gui/widgets/__init__.py
hardware_control/gui/widgets/connection_status.py
hardware_control/gui/widgets/data_widget.py
hardware_control/gui/widgets/function_runner.py
hardware_control/gui/widgets/hc_widgets.py
hardware_control/gui/widgets/plot.py
hardware_control/gui/widgets/qtconsole.py
hardware_control/gui/widgets/scan_widget.py
hardware_control/gui/widgets/trace_plotter.py
hardware_control/icons/BWlim.png
hardware_control/icons/arrow.png
hardware_control/icons/async_label.png
hardware_control/icons/autosave_label.png
hardware_control/icons/blue_ind.svg
hardware_control/icons/burst.png
hardware_control/icons/button-power-off.svg
hardware_control/icons/button-power-on.svg
hardware_control/icons/button-power-unknown.svg
hardware_control/icons/calibration-error.svg
hardware_control/icons/ccurrent_label.svg
hardware_control/icons/channel1_yellow.png
hardware_control/icons/channel2_green.png
hardware_control-3.1.0.dist-info/LICENSE
hardware_control-3.1.0.dist-info/METADATA
hardware_control-3.1.0.dist-info/WHEEL
hardware_control-3.1.0.dist-info/top_level.txt
hardware_control-3.1.0.dist-info/RECORD
