Metadata-Version: 2.1
Name: hardware-control
Version: 3.1.0
Author-email: Arun Persaud <apersaud@lbl.gov>, Ariel Amsellem <ajamsellem@lbl.gov>, Brian Mak <brianmak@lbl.gov>, Mauricio Ayllon Unzueta <mayllonu@lbl.gov>, Brian Wynne <bwynne@lbl.gov>, Grant Giesbrecht <ggiesbrecht@lbl.gov>, Timo Bauer <TimoBauer@lbl.gov>, Zhihao Qin <zqin@lbl.gov>, Arfon Smith <arfon.smith@gmail.com>, Sara Matsuo Saib <smsaib@lbl.gov>, Caroline Egan <cegan@lbl.gov>, Schuyler Freeman <skyfreeman@lbl.gov>
License: Copyright (c) 2019, The Regents of the University of California,
Project-URL: documentation, https://hardware-control.readthedocs.io/
Project-URL: homepage, https://bitbucket.org/berkeleylab/hardware-control
Project-URL: issues, https://bitbucket.org/berkeleylab/hardware-control/issues
Project-URL: changelog, https://bitbucket.org/berkeleylab/hardware-control/src/main/CHANGELOG.md
Classifier: Programming Language :: Python :: 3
Classifier: Operating System :: OS Independent
Classifier: Development Status :: 5 - Production/Stable
Classifier: License :: OSI Approved :: BSD License
Classifier: Intended Audience :: Science/Research
Classifier: Programming Language :: Python :: 3.9
Classifier: Programming Language :: Python :: 3.10
Classifier: Programming Language :: Python :: 3.11
Classifier: Programming Language :: Python :: 3.12
Classifier: Topic :: Scientific/Engineering :: Physics
Requires-Python: >=3.9
License-File: LICENSE
Requires-Dist: docopt
Requires-Dist: matplotlib
Requires-Dist: nidaqmx >=0.6.4
Requires-Dist: numpy
Requires-Dist: pandas
Requires-Dist: picoscope
Requires-Dist: pymodbus >=3.0.0
Requires-Dist: PyQt6
Requires-Dist: pyqtgraph
Requires-Dist: pytest
Requires-Dist: PyVISA
Requires-Dist: qtconsole >=5.3.2
Requires-Dist: recommonmark
Requires-Dist: scipy
Requires-Dist: setuptools
Requires-Dist: setuptools-scm
Requires-Dist: Sphinx
Requires-Dist: sphinx-rtd-theme
Requires-Dist: pyzmq
